fastapi_app_builder/__init__.py
fastapi_app_builder/builder.py
fastapi_app_builder/container.py
fastapi_app_builder/exceptions.py
fastapi_app_builder/lifetime.py
fastapi_app_builder/middleware.py
fastapi_app_builder/patch.py
fastapi_app_builder/py.typed
fastapi_app_builder/resolver.py
fastapi_app_builder/router.py
fastapi_app_builder/validation.py
fastapi_app_builder/wrapper.py
fastapi_app_builder/installers/__init__.py
fastapi_app_builder/installers/cors.py
fastapi_app_builder/installers/database.py
fastapi_app_builder-0.1.0b1.dist-info/METADATA
fastapi_app_builder-0.1.0b1.dist-info/WHEEL
fastapi_app_builder-0.1.0b1.dist-info/licenses/LICENSE
fastapi_app_builder-0.1.0b1.dist-info/RECORD
