Metadata-Version: 2.4
Name: fastapi-app-builder
Version: 0.1.0b1
Summary: ASP.NET Core-style dependency injection for FastAPI
Project-URL: Homepage, https://github.com/Saurus119/fastapi-builder
Project-URL: Documentation, https://github.com/Saurus119/fastapi-builder#readme
Project-URL: Repository, https://github.com/Saurus119/fastapi-builder
Project-URL: Issues, https://github.com/Saurus119/fastapi-builder/issues
Author-email: Jan Klečka <jan.klecka12@gmail.com>
License: MIT
License-File: LICENSE
Keywords: asp.net,dependency-injection,di,dotnet,fastapi,ioc
Classifier: Development Status :: 4 - Beta
Classifier: Framework :: FastAPI
Classifier: Intended Audience :: Developers
Classifier: License :: OSI Approved :: MIT License
Classifier: Programming Language :: Python :: 3
Classifier: Programming Language :: Python :: 3.10
Classifier: Programming Language :: Python :: 3.11
Classifier: Programming Language :: Python :: 3.12
Classifier: Programming Language :: Python :: 3.13
Classifier: Topic :: Software Development :: Libraries :: Python Modules
Classifier: Typing :: Typed
Requires-Python: >=3.10
Requires-Dist: fastapi>=0.100.0
Provides-Extra: all
Requires-Dist: sqlalchemy>=2.0.0; extra == 'all'
Provides-Extra: dev
Requires-Dist: coverage>=7.0.0; extra == 'dev'
Requires-Dist: httpx>=0.27.0; extra == 'dev'
Requires-Dist: mypy>=1.9.0; extra == 'dev'
Requires-Dist: pytest-asyncio>=0.23.0; extra == 'dev'
Requires-Dist: pytest>=8.0.0; extra == 'dev'
Requires-Dist: ruff>=0.8.0; extra == 'dev'
Provides-Extra: sqlalchemy
Requires-Dist: sqlalchemy>=2.0.0; extra == 'sqlalchemy'
